visioncapsule_tools/__init__.py
visioncapsule_tools/capsule_downloader.py
visioncapsule_tools/cli.py
visioncapsule_tools/command_utils.py
visioncapsule_tools/print_utils.py
visioncapsule_tools/translations/portal.en.yml
visioncapsule_tools-0.5.1.dist-info/COPYING
visioncapsule_tools-0.5.1.dist-info/METADATA
visioncapsule_tools-0.5.1.dist-info/WHEEL
visioncapsule_tools-0.5.1.dist-info/entry_points.txt
visioncapsule_tools-0.5.1.dist-info/RECORD
