Metadata-Version: 2.1
Name: visioncapsule-tools
Version: 0.5.1
Summary: A tool to help users easily download VisionCapsules
License: BSD License
Author: Stephen Li
Author-email: stephen@aotu.ai
Requires-Python: >=3.9,<4.0
Classifier: License :: OSI Approved :: BSD License
Classifier: License :: Other/Proprietary License
Classifier: Programming Language :: Python :: 3
Classifier: Programming Language :: Python :: 3.9
Classifier: Programming Language :: Python :: 3.10
Classifier: Programming Language :: Python :: 3.11
Classifier: Programming Language :: Python :: 3.12
Classifier: Programming Language :: Python :: 3.13
Requires-Dist: PyYAML (>=6.0.2,<7.0.0)
Requires-Dist: beautifulsoup4 (>=4.9.3,<5.0.0)
Requires-Dist: brainframe_apps (>=0.5.1,<0.6.0)
Requires-Dist: lxml (>=4.6.3,<5.0.0)
Requires-Dist: python_i18n (>=0.3.9,<0.4.0)
Requires-Dist: questionary (>=2.0.1,<3.0.0)
Requires-Dist: requests (>=2.32.3,<3.0.0)
Requires-Dist: wget (>=3.2,<4.0)
